tor_python_easy/__init__.py
tor_python_easy/tor_control_port_client.py
tor_python_easy/tor_socks_get_ip_client.py
tor_python_easy-0.1.6.dist-info/LICENSE.md
tor_python_easy-0.1.6.dist-info/METADATA
tor_python_easy-0.1.6.dist-info/WHEEL
tor_python_easy-0.1.6.dist-info/RECORD
