Metadata-Version: 2.1
Name: tor-python-easy
Version: 0.1.6
Summary: Simple library to manage tor proxy and IP changes
Home-page: https://github.com/markowanga/tor-python-easy
Author: Marcin Wątroba
Author-email: markowanga@gmail.com
Requires-Python: >=3.8,<4.0
Classifier: Programming Language :: Python :: 3
Classifier: Programming Language :: Python :: 3.8
Classifier: Programming Language :: Python :: 3.9
Classifier: Programming Language :: Python :: 3.10
Classifier: Programming Language :: Python :: 3.11
Requires-Dist: PySocks (>=1.7.1,<2.0.0)
Requires-Dist: requests (>=2.31.0,<3.0.0)
